<?xml version="1.0" encoding="utf-8" ?>
<dwsync>
<file name="MeTube.css" server="metube-1223456.duckdns.org" local="131999093634649062" remote="131999237400000000" Dst="2" />
<file name="accountimg.jpg" server="metube-1223456.duckdns.org" local="131993834372367300" remote="131994032400000000" Dst="2" />
<file name="MeTube_GlobalHeader.php" server="metube-1223456.duckdns.org" local="131999125477421901" remote="131999269200000000" Dst="2" />
<file name="MeTube.php" server="metube-1223456.duckdns.org" local="132000158335046630" remote="132000301800000000" Dst="2" />
<file name="MeTubeAccount.php" server="metube-1223456.duckdns.org" local="132000835122279617" remote="132000978600000000" Dst="2" />
<file name="MetubeSignIn.php" server="metube-1223456.duckdns.org" local="131994765117916385" remote="131994909000000000" Dst="2" />
<file name="MeTubeSignIn.php" server="metube-1223456.duckdns.org" local="132000715235804125" remote="132000859200000000" Dst="2" />
<file name="MeTubeCreate.php" server="metube-1223456.duckdns.org" local="132000118047344020" remote="132000261600000000" Dst="2" />
<file name="MeTubeSearch.php" server="metube-1223456.duckdns.org" local="131999086149754898" remote="131999229600000000" Dst="2" />
<file name="MeTubeView.php" server="metube-1223456.duckdns.org" local="132000825867244585" remote="132000969600000000" Dst="2" />
<file name="MeTubeUpload.php" server="metube-1223456.duckdns.org" local="132000715460578660" remote="132000859200000000" Dst="2" />
<file name="config.php" server="metube-1223456.duckdns.org" local="131994602254435006" remote="131994752400000000" Dst="2" />
<file name="mysqlClass.inc.php" server="metube-1223456.duckdns.org" local="129091676160000000" remote="131994752400000000" Dst="2" />
<file name="function.php" server="metube-1223456.duckdns.org" local="132000721948653219" remote="132000865800000000" Dst="2" />
<file name="MeTubePlaylist.php" server="metube-1223456.duckdns.org" local="132000713674359765" remote="132000857400000000" Dst="2" />
<file name="MeTubeMessage.php" server="metube-1223456.duckdns.org" local="132000715317113546" remote="132000859200000000" Dst="2" />
<file name="MeTubeReply.php" server="metube-1223456.duckdns.org" local="132000715269077665" remote="132000859200000000" Dst="2" />
<file name="operation.php" server="metube-1223456.duckdns.org" local="132000149777738832" remote="132000293400000000" Dst="2" />
</dwsync>